onot/__init__.py
onot/__main__.py
onot/generating/__init__.py
onot/generating/generate.py
onot/generating/html.py
onot/generating/html_resource.py
onot/gui/__init__.py
onot/gui/onot_app.py
onot/gui/widget_finish.py
onot/gui/widget_home.py
onot/gui/widget_progress.py
onot/log/__init__.py
onot/log/log_setting.py
onot/parsing/__init__.py
onot/parsing/excel.py
onot/parsing/parse.py
onot/parsing/parser.py
onot/parsing/rdf_xml.py
onot/parsing/spdx_license.py
onot/tools/__init__.py
onot/tools/create_notice.py
test/__init__.py
test/test_get_spdx_license.py
test/test_parsing_excel.py
test/test_parsing_rdf_xml.py
onot-1.0.0.dist-info/LICENSE
onot-1.0.0.dist-info/METADATA
onot-1.0.0.dist-info/WHEEL
onot-1.0.0.dist-info/entry_points.txt
onot-1.0.0.dist-info/top_level.txt
onot-1.0.0.dist-info/RECORD
